timecamp-server.py
timecamp_mcp_server/__init__.py
timecamp_mcp_server/__main__.py
timecamp_mcp_server-0.1.1.dist-info/licenses/LICENSE
timecamp_mcp_server-0.1.1.dist-info/METADATA
timecamp_mcp_server-0.1.1.dist-info/WHEEL
timecamp_mcp_server-0.1.1.dist-info/entry_points.txt
timecamp_mcp_server-0.1.1.dist-info/top_level.txt
timecamp_mcp_server-0.1.1.dist-info/RECORD
