Metadata-Version: 2.4
Name: timecamp-mcp-server
Version: 0.1.1
Summary: A Model Context Protocol server for TimeCamp time tracking integration
Author-email: Keenan Keeling <kkeeling@gmail.com>
License: MIT
Project-URL: Homepage, https://github.com/kkeeling/timecamp-mcp-server
Project-URL: Repository, https://github.com/kkeeling/timecamp-mcp-server.git
Project-URL: Issues, https://github.com/kkeeling/timecamp-mcp-server/issues
Classifier: Development Status :: 3 - Alpha
Classifier: Intended Audience :: Developers
Classifier: License :: OSI Approved :: MIT License
Classifier: Programming Language :: Python :: 3
Classifier: Programming Language :: Python :: 3.8
Classifier: Programming Language :: Python :: 3.9
Classifier: Programming Language :: Python :: 3.10
Classifier: Programming Language :: Python :: 3.11
Classifier: Programming Language :: Python :: 3.12
Requires-Python: >=3.8
License-File: LICENSE
Requires-Dist: fastmcp>=0.8.0
Requires-Dist: httpx>=0.27.0
Requires-Dist: pydantic>=2.0.0
Requires-Dist: python-dotenv>=1.0.0
Requires-Dist: rapidfuzz>=3.0.0
Dynamic: license-file
